docker_assemble/__init__.py
docker_assemble/docker_utils.py
docker_assemble/image_exporter.py
docker_assemble/main.py
docker_assemble-0.5.0.dist-info/METADATA
docker_assemble-0.5.0.dist-info/WHEEL
docker_assemble-0.5.0.dist-info/entry_points.txt
docker_assemble-0.5.0.dist-info/top_level.txt
docker_assemble-0.5.0.dist-info/RECORD
