Metadata-Version: 2.4
Name: docker-assemble
Version: 0.5.0
Summary: A CLI tool to extract and analyze Docker images
Author: Sina
License: Apache-2.0
Requires-Python: >=3.8
Requires-Dist: docker>=6.0.0
